<?xml version="1.0" standalone="yes"?>
<beast version="1.10.4">


	<taxa id="taxa">

		<taxon id="EPI_ISL_623074">
			<date value="2020.3643835616438" direction="forwards" units="years"/>
			<attr name="host2">
				Dom-gal
			</attr>
			<attr name="loc">
				36.23 42.24
			</attr>
		</taxon>


		<taxon id="EPI_ISL_637098">
			<date value="2020.5835616438355" direction="forwards" units="years"/>
			<attr name="host2">
				Dom-ans
			</attr>
			<attr name="loc">
				54.43 60.88
			</attr>
		</taxon>


		<taxon id="EPI_ISL_644122">
			<date value="2020.6191780821919" direction="forwards" units="years"/>
			<attr name="host2">
				Dom-ans
			</attr>
			<attr name="loc">
				55.06 73.72
			</attr>
		</taxon>


		<taxon id="EPI_ISL_644124">
			<date value="2020.6191780821919" direction="forwards" units="years"/>
			<attr name="host2">
				Dom-ans
			</attr>
			<attr name="loc">
				55.06 73.72
			</attr>
		</taxon>


		<taxon id="EPI_ISL_644123">
			<date value="2020.6191780821919" direction="forwards" units="years"/>
			<attr name="host2">
				Dom-gal
			</attr>
			<attr name="loc">
				55.06 73.72
			</attr>
		</taxon>


		<taxon id="EPI_ISL_626650">
			<date value="2020.6301369863013" direction="forwards" units="years"/>
			<attr name="host2">
				Dom-ans
			</attr>
			<attr name="loc">
				55.06 73.72
			</attr>
		</taxon>


		<taxon id="EPI_ISL_644138">
			<date value="2020.6301369863013" direction="forwards" units="years"/>
			<attr name="host2">
				Waterfowl
			</attr>
			<attr name="loc">
				55.06 73.72
			</attr>
		</taxon>


		<taxon id="EPI_ISL_644134">
			<date value="2020.6301369863013" direction="forwards" units="years"/>
			<attr name="host2">
				Dom-gal
			</attr>
			<attr name="loc">
				55.06 73.72
			</attr>
		</taxon>


		<taxon id="EPI_ISL_644140">
			<date value="2020.6301369863013" direction="forwards" units="years"/>
			<attr name="host2">
				Dom-gal
			</attr>
			<attr name="loc">
				55.06 73.72
			</attr>
		</taxon>


		<taxon id="EPI_ISL_644130">
			<date value="2020.6301369863013" direction="forwards" units="years"/>
			<attr name="host2">
				Dom-ans
			</attr>
			<attr name="loc">
				55.06 73.72
			</attr>
		</taxon>


		<taxon id="EPI_ISL_644142">
			<date value="2020.6301369863013" direction="forwards" units="years"/>
			<attr name="host2">
				Dom-ans
			</attr>
			<attr name="loc">
				55.06 73.72
			</attr>
		</taxon>


		<taxon id="EPI_ISL_654839">
			<date value="2020.6575342465753" direction="forwards" units="years"/>
			<attr name="host2">
				Dom-ans
			</attr>
			<attr name="loc">
				55.45 65.12
			</attr>
		</taxon>


		<taxon id="EPI_ISL_739685">
			<date value="2020.66301369863" direction="forwards" units="years"/>
			<attr name="host2">
				Waterfowl
			</attr>
			<attr name="loc">
				55.06 73.72
			</attr>
		</taxon>


		<taxon id="EPI_ISL_654830">
			<date value="2020.676712328767" direction="forwards" units="years"/>
			<attr name="host2">
				Dom-gal
			</attr>
			<attr name="loc">
				55.06 73.72
			</attr>
		</taxon>


		<taxon id="EPI_ISL_654831">
			<date value="2020.676712328767" direction="forwards" units="years"/>
			<attr name="host2">
				Dom-ans
			</attr>
			<attr name="loc">
				55.06 73.72
			</attr>
		</taxon>


		<taxon id="EPI_ISL_654829">
			<date value="2020.676712328767" direction="forwards" units="years"/>
			<attr name="host2">
				Dom-ans
			</attr>
			<attr name="loc">
				55.06 73.72
			</attr>
		</taxon>


		<taxon id="EPI_ISL_654826">
			<date value="2020.676712328767" direction="forwards" units="years"/>
			<attr name="host2">
				Dom-ans
			</attr>
			<attr name="loc">
				55.06 73.72
			</attr>
		</taxon>


		<taxon id="EPI_ISL_661178">
			<date value="2020.695890410959" direction="forwards" units="years"/>
			<attr name="host2">
				Waterfowl
			</attr>
			<attr name="loc">
				56.96 66.95
			</attr>
		</taxon>


		<taxon id="EPI_ISL_739684">
			<date value="2020.7095890410958" direction="forwards" units="years"/>
			<attr name="host2">
				Waterfowl
			</attr>
			<attr name="loc">
				55.45 80.1
			</attr>
		</taxon>


		<taxon id="EPI_ISL_654821">
			<date value="2020.7095890410958" direction="forwards" units="years"/>
			<attr name="host2">
				Dom-gal
			</attr>
			<attr name="loc">
				51.84 46.75
			</attr>
		</taxon>


		<taxon id="EPI_ISL_626649">
			<date value="2020.717808219178" direction="forwards" units="years"/>
			<attr name="host2">
				Dom-ans
			</attr>
			<attr name="loc">
				51.84 46.75
			</attr>
		</taxon>


		<taxon id="EPI_ISL_739686">
			<date value="2020.717808219178" direction="forwards" units="years"/>
			<attr name="host2">
				Dom-gal
			</attr>
			<attr name="loc">
				48.02 66.92
			</attr>
		</taxon>


		<taxon id="EPI_ISL_615073">
			<date value="2020.7205479452055" direction="forwards" units="years"/>
			<attr name="host2">
				Dom-ans
			</attr>
			<attr name="loc">
				48.02 66.92
			</attr>
		</taxon>


		<taxon id="EPI_ISL_739690">
			<date value="2020.7232876712328" direction="forwards" units="years"/>
			<attr name="host2">
				Dom-gal
			</attr>
			<attr name="loc">
				55.45 80.1
			</attr>
		</taxon>


		<taxon id="EPI_ISL_739688">
			<date value="2020.7287671232878" direction="forwards" units="years"/>
			<attr name="host2">
				Dom-gal
			</attr>
			<attr name="loc">
				55.45 80.1
			</attr>
		</taxon>


		<taxon id="EPI_ISL_739689">
			<date value="2020.7287671232878" direction="forwards" units="years"/>
			<attr name="host2">
				Dom-gal
			</attr>
			<attr name="loc">
				55.45 80.1
			</attr>
		</taxon>


		<taxon id="EPI_ISL_614401">
			<date value="2020.731506849315" direction="forwards" units="years"/>
			<attr name="host2">
				Waterfowl
			</attr>
			<attr name="loc">
				51.92 69.41
			</attr>
		</taxon>


		<taxon id="EPI_ISL_615072">
			<date value="2020.7369863013698" direction="forwards" units="years"/>
			<attr name="host2">
				Dom-ans
			</attr>
			<attr name="loc">
				53.22 63.64
			</attr>
		</taxon>


		<taxon id="EPI_ISL_1114735">
			<date value="2020.7397260273972" direction="forwards" units="years"/>
			<attr name="host2">
				Dom-gal
			</attr>
			<attr name="loc">
				56.96 66.95
			</attr>
		</taxon>


		<taxon id="EPI_ISL_625672">
			<date value="2020.7972602739726" direction="forwards" units="years"/>
			<attr name="host2">
				Waterfowl
			</attr>
			<attr name="loc">
				49.19 119.76
			</attr>
		</taxon>


		<taxon id="EPI_ISL_1114746">
			<date value="2020.8191780821917" direction="forwards" units="years"/>
			<attr name="host2">
				Dom-gal
			</attr>
			<attr name="loc">
				47.69 41.83
			</attr>
		</taxon>


		<taxon id="EPI_ISL_603132">
			<date value="2020.827397260274" direction="forwards" units="years"/>
			<attr name="host2">
				Dom-gal
			</attr>
			<attr name="loc">
				52.05 5.87
			</attr>
		</taxon>


		<taxon id="EPI_ISL_710508">
			<date value="2020.8328767123287" direction="forwards" units="years"/>
			<attr name="host2">
				Waterfowl
			</attr>
			<attr name="loc">
				51.86 -2.24
			</attr>
		</taxon>


		<taxon id="EPI_ISL_641377">
			<date value="2020.841095890411" direction="forwards" units="years"/>
			<attr name="host2">
				Dom-gal
			</attr>
			<attr name="loc">
				52.52 4.79
			</attr>
		</taxon>


		<taxon id="EPI_ISL_710507">
			<date value="2020.8438356164384" direction="forwards" units="years"/>
			<attr name="host2">
				Waterfowl
			</attr>
			<attr name="loc">
				51.86 -2.24
			</attr>
		</taxon>


		<taxon id="EPI_ISL_984690">
			<date value="2020.8520547945207" direction="forwards" units="years"/>
			<attr name="host2">
				Other
			</attr>
			<attr name="loc">
				55.33 9.09
			</attr>
		</taxon>


		<taxon id="EPI_ISL_1575129">
			<date value="2020.8520547945207" direction="forwards" units="years"/>
			<attr name="host2">
				Other
			</attr>
			<attr name="loc">
				51.92 4.48
			</attr>
		</taxon>


		<taxon id="EPI_ISL_1575135">
			<date value="2020.8520547945207" direction="forwards" units="years"/>
			<attr name="host2">
				Waterfowl
			</attr>
			<attr name="loc">
				51.92 4.48
			</attr>
		</taxon>


		<taxon id="EPI_ISL_984693">
			<date value="2020.854794520548" direction="forwards" units="years"/>
			<attr name="host2">
				Waterfowl
			</attr>
			<attr name="loc">
				55.46 11.72
			</attr>
		</taxon>


		<taxon id="EPI_ISL_1123357">
			<date value="2020.8575342465754" direction="forwards" units="years"/>
			<attr name="host2">
				Waterfowl
			</attr>
			<attr name="loc">
				52.96 -0.16
			</attr>
		</taxon>


		<taxon id="EPI_ISL_1123359">
			<date value="2020.86301369863" direction="forwards" units="years"/>
			<attr name="host2">
				Waterfowl
			</attr>
			<attr name="loc">
				50.73 -2.34
			</attr>
		</taxon>


		<taxon id="EPI_ISL_668456">
			<date value="2020.86301369863" direction="forwards" units="years"/>
			<attr name="host2">
				Other
			</attr>
			<attr name="loc">
				55.99 13.6
			</attr>
		</taxon>


		<taxon id="EPI_ISL_641395">
			<date value="2020.8657534246574" direction="forwards" units="years"/>
			<attr name="host2">
				Dom-gal
			</attr>
			<attr name="loc">
				52.52 4.79
			</attr>
		</taxon>


		<taxon id="EPI_ISL_668457">
			<date value="2020.868493150685" direction="forwards" units="years"/>
			<attr name="host2">
				Waterfowl
			</attr>
			<attr name="loc">
				55.99 13.6
			</attr>
		</taxon>


		<taxon id="EPI_ISL_647969">
			<date value="2020.8712328767124" direction="forwards" units="years"/>
			<attr name="host2">
				Dom-gal
			</attr>
			<attr name="loc">
				55.99 13.6
			</attr>
		</taxon>


		<taxon id="EPI_ISL_683593">
			<date value="2020.8739726027397" direction="forwards" units="years"/>
			<attr name="host2">
				Waterfowl
			</attr>
			<attr name="loc">
				45.44 12.32
			</attr>
		</taxon>


		<taxon id="EPI_ISL_984688">
			<date value="2020.876712328767" direction="forwards" units="years"/>
			<attr name="host2">
				Waterfowl
			</attr>
			<attr name="loc">
				55.33 9.09
			</attr>
		</taxon>


		<taxon id="EPI_ISL_666890">
			<date value="2020.8821917808218" direction="forwards" units="years"/>
			<attr name="host2">
				Dom-gal
			</attr>
			<attr name="loc">
				46.16 16.84
			</attr>
		</taxon>


		<taxon id="EPI_ISL_1665263">
			<date value="2020.8821917808218" direction="forwards" units="years"/>
			<attr name="host2">
				Waterfowl
			</attr>
			<attr name="loc">
				46.15 15.0
			</attr>
		</taxon>


		<taxon id="EPI_ISL_1665272">
			<date value="2020.8821917808218" direction="forwards" units="years"/>
			<attr name="host2">
				Other
			</attr>
			<attr name="loc">
				40.35 18.18
			</attr>
		</taxon>


		<taxon id="EPI_ISL_710512">
			<date value="2020.8849315068494" direction="forwards" units="years"/>
			<attr name="host2">
				Waterfowl
			</attr>
			<attr name="loc">
				51.86 -2.24
			</attr>
		</taxon>


		<taxon id="EPI_ISL_661177">
			<date value="2020.9013698630138" direction="forwards" units="years"/>
			<attr name="host2">
				Dom-gal
			</attr>
			<attr name="loc">
				52.28 17.35
			</attr>
		</taxon>


		<taxon id="EPI_ISL_1009698">
			<date value="2020.9041095890411" direction="forwards" units="years"/>
			<attr name="host2">
				Waterfowl
			</attr>
			<attr name="loc">
				37.41 127.52
			</attr>
		</taxon>


		<taxon id="EPI_ISL_1665251">
			<date value="2020.9123287671232" direction="forwards" units="years"/>
			<attr name="host2">
				Waterfowl
			</attr>
			<attr name="loc">
				45.07 11.79
			</attr>
		</taxon>


		<taxon id="EPI_ISL_956411">
			<date value="2020.9150684931508" direction="forwards" units="years"/>
			<attr name="host2">
				Waterfowl
			</attr>
			<attr name="loc">
				45.44 12.32
			</attr>
		</taxon>


		<taxon id="EPI_ISL_1295639">
			<date value="2020.9178082191781" direction="forwards" units="years"/>
			<attr name="host2">
				Dom-gal
			</attr>
			<attr name="loc">
				60.47 8.47
			</attr>
		</taxon>


		<taxon id="EPI_ISL_779129">
			<date value="2020.9205479452055" direction="forwards" units="years"/>
			<attr name="host2">
				Dom-gal
			</attr>
			<attr name="loc">
				51.89 21.0
			</attr>
		</taxon>


		<taxon id="EPI_ISL_1665264">
			<date value="2020.9232876712329" direction="forwards" units="years"/>
			<attr name="host2">
				Waterfowl
			</attr>
			<attr name="loc">
				46.15 15.0
			</attr>
		</taxon>


		<taxon id="EPI_ISL_956408">
			<date value="2020.9287671232876" direction="forwards" units="years"/>
			<attr name="host2">
				Waterfowl
			</attr>
			<attr name="loc">
				45.44 12.32
			</attr>
		</taxon>


		<taxon id="EPI_ISL_766053">
			<date value="2020.9287671232876" direction="forwards" units="years"/>
			<attr name="host2">
				Dom-gal
			</attr>
			<attr name="loc">
				52.61 0.89
			</attr>
		</taxon>


		<taxon id="EPI_ISL_846603">
			<date value="2020.9287671232876" direction="forwards" units="years"/>
			<attr name="host2">
				Dom-gal
			</attr>
			<attr name="loc">
				52.28 17.35
			</attr>
		</taxon>


		<taxon id="EPI_ISL_846604">
			<date value="2020.9369863013699" direction="forwards" units="years"/>
			<attr name="host2">
				Dom-gal
			</attr>
			<attr name="loc">
				51.89 21.0
			</attr>
		</taxon>


		<taxon id="EPI_ISL_1220094">
			<date value="2020.9424657534246" direction="forwards" units="years"/>
			<attr name="host2">
				Waterfowl
			</attr>
			<attr name="loc">
				53.47 15.18
			</attr>
		</taxon>


		<taxon id="EPI_ISL_1665265">
			<date value="2020.9424657534246" direction="forwards" units="years"/>
			<attr name="host2">
				Waterfowl
			</attr>
			<attr name="loc">
				46.15 15.0
			</attr>
		</taxon>


		<taxon id="EPI_ISL_985187">
			<date value="2020.945205479452" direction="forwards" units="years"/>
			<attr name="host2">
				Dom-ans
			</attr>
			<attr name="loc">
				34.87 126.99
			</attr>
		</taxon>


		<taxon id="EPI_ISL_1665266">
			<date value="2020.945205479452" direction="forwards" units="years"/>
			<attr name="host2">
				Waterfowl
			</attr>
			<attr name="loc">
				46.15 15.0
			</attr>
		</taxon>


		<taxon id="EPI_ISL_1114749">
			<date value="2020.9479452054795" direction="forwards" units="years"/>
			<attr name="host2">
				Dom-gal
			</attr>
			<attr name="loc">
				44.67 43.52
			</attr>
		</taxon>


		<taxon id="EPI_ISL_1039236">
			<date value="2020.9506849315069" direction="forwards" units="years"/>
			<attr name="host2">
				Dom-gal
			</attr>
			<attr name="loc">
				46.13 48.06
			</attr>
		</taxon>


		<taxon id="EPI_ISL_1009707">
			<date value="2020.9561643835616" direction="forwards" units="years"/>
			<attr name="host2">
				Waterfowl
			</attr>
			<attr name="loc">
				36.8 127.7
			</attr>
		</taxon>


		<taxon id="EPI_ISL_846624">
			<date value="2020.958904109589" direction="forwards" units="years"/>
			<attr name="host2">
				Waterfowl
			</attr>
			<attr name="loc">
				54.29 18.15
			</attr>
		</taxon>


		<taxon id="EPI_ISL_1009708">
			<date value="2020.958904109589" direction="forwards" units="years"/>
			<attr name="host2">
				Waterfowl
			</attr>
			<attr name="loc">
				37.41 127.52
			</attr>
		</taxon>


		<taxon id="EPI_ISL_846623">
			<date value="2020.9616438356165" direction="forwards" units="years"/>
			<attr name="host2">
				Waterfowl
			</attr>
			<attr name="loc">
				54.29 18.15
			</attr>
		</taxon>


		<taxon id="EPI_ISL_1123350">
			<date value="2020.964383561644" direction="forwards" units="years"/>
			<attr name="host2">
				Dom-gal
			</attr>
			<attr name="loc">
				50.73 -2.34
			</attr>
		</taxon>


		<taxon id="EPI_ISL_1123351">
			<date value="2020.964383561644" direction="forwards" units="years"/>
			<attr name="host2">
				Dom-ans
			</attr>
			<attr name="loc">
				52.61 0.89
			</attr>
		</taxon>


		<taxon id="EPI_ISL_985205">
			<date value="2020.9835616438356" direction="forwards" units="years"/>
			<attr name="host2">
				Dom-ans
			</attr>
			<attr name="loc">
				36.52 126.8
			</attr>
		</taxon>


		<taxon id="EPI_ISL_985207">
			<date value="2020.986301369863" direction="forwards" units="years"/>
			<attr name="host2">
				Dom-gal
			</attr>
			<attr name="loc">
				36.49 128.89
			</attr>
		</taxon>


		<taxon id="EPI_ISL_1123353">
			<date value="2020.9890410958903" direction="forwards" units="years"/>
			<attr name="host2">
				Dom-ans
			</attr>
			<attr name="loc">
				52.61 0.89
			</attr>
		</taxon>


		<taxon id="EPI_ISL_1123354">
			<date value="2020.9945205479453" direction="forwards" units="years"/>
			<attr name="host2">
				Dom-gal
			</attr>
			<attr name="loc">
				50.72 -3.53
			</attr>
		</taxon>


		<taxon id="EPI_ISL_1009680">
			<date value="2020.9945205479453" direction="forwards" units="years"/>
			<attr name="host2">
				Other
			</attr>
			<attr name="loc">
				37.41 127.52
			</attr>
		</taxon>


		<taxon id="EPI_ISL_1009682">
			<date value="2020.9972602739726" direction="forwards" units="years"/>
			<attr name="host2">
				Dom-gal
			</attr>
			<attr name="loc">
				37.41 127.52
			</attr>
		</taxon>


		<taxon id="EPI_ISL_977582">
			<date value="2020.9972602739726" direction="forwards" units="years"/>
			<attr name="host2">
				Dom-ans
			</attr>
			<attr name="loc">
				35.89 117.92
			</attr>
		</taxon>


		<taxon id="EPI_ISL_1009685">
			<date value="2021.0" direction="forwards" units="years"/>
			<attr name="host2">
				Dom-ans
			</attr>
			<attr name="loc">
				35.72 127.15
			</attr>
		</taxon>


		<taxon id="EPI_ISL_1114752">
			<date value="2021.0027397260274" direction="forwards" units="years"/>
			<attr name="host2">
				Waterfowl
			</attr>
			<attr name="loc">
				43.05 44.29
			</attr>
		</taxon>


		<taxon id="EPI_ISL_977595">
			<date value="2021.0027397260274" direction="forwards" units="years"/>
			<attr name="host2">
				Dom-ans
			</attr>
			<attr name="loc">
				30.26 102.81
			</attr>
		</taxon>


		<taxon id="EPI_ISL_1009688">
			<date value="2021.0027397260274" direction="forwards" units="years"/>
			<attr name="host2">
				Dom-gal
			</attr>
			<attr name="loc">
				34.87 126.99
			</attr>
		</taxon>


		<taxon id="EPI_ISL_1009689">
			<date value="2021.0082191780823" direction="forwards" units="years"/>
			<attr name="host2">
				Dom-gal
			</attr>
			<attr name="loc">
				36.52 126.8
			</attr>
		</taxon>


		<taxon id="EPI_ISL_1009690">
			<date value="2021.0109589041097" direction="forwards" units="years"/>
			<attr name="host2">
				Dom-gal
			</attr>
			<attr name="loc">
				36.52 126.8
			</attr>
		</taxon>


		<taxon id="EPI_ISL_996003">
			<date value="2021.013698630137" direction="forwards" units="years"/>
			<attr name="host2">
				Dom-gal
			</attr>
			<attr name="loc">
				54.79 -6.49
			</attr>
		</taxon>


		<taxon id="EPI_ISL_1009711">
			<date value="2021.0164383561644" direction="forwards" units="years"/>
			<attr name="host2">
				Dom-ans
			</attr>
			<attr name="loc">
				34.87 126.99
			</attr>
		</taxon>


		<taxon id="EPI_ISL_2234811">
			<date value="2021.0191780821917" direction="forwards" units="years"/>
			<attr name="host2">
				Waterfowl
			</attr>
			<attr name="loc">
				40.46 -3.75
			</attr>
		</taxon>


		<taxon id="EPI_ISL_2234813">
			<date value="2021.0191780821917" direction="forwards" units="years"/>
			<attr name="host2">
				Other
			</attr>
			<attr name="loc">
				40.46 -3.75
			</attr>
		</taxon>


		<taxon id="EPI_ISL_1665256">
			<date value="2021.021917808219" direction="forwards" units="years"/>
			<attr name="host2">
				Waterfowl
			</attr>
			<attr name="loc">
				48.72 21.26
			</attr>
		</taxon>


		<taxon id="EPI_ISL_1009694">
			<date value="2021.0246575342467" direction="forwards" units="years"/>
			<attr name="host2">
				Dom-ans
			</attr>
			<attr name="loc">
				35.46 128.21
			</attr>
		</taxon>


		<taxon id="EPI_ISL_2234817">
			<date value="2021.035616438356" direction="forwards" units="years"/>
			<attr name="host2">
				Waterfowl
			</attr>
			<attr name="loc">
				45.94 24.97
			</attr>
		</taxon>


		<taxon id="EPI_ISL_956368">
			<date value="2021.0520547945205" direction="forwards" units="years"/>
			<attr name="host2">
				Waterfowl
			</attr>
			<attr name="loc">
				48.95 14.44
			</attr>
		</taxon>


		<taxon id="EPI_ISL_1191587">
			<date value="2021.0602739726028" direction="forwards" units="years"/>
			<attr name="host2">
				Dom-gal
			</attr>
			<attr name="loc">
				48.95 14.44
			</attr>
		</taxon>


		<taxon id="EPI_ISL_1180234">
			<date value="2021.0657534246575" direction="forwards" units="years"/>
			<attr name="host2">
				Waterfowl
			</attr>
			<attr name="loc">
				48.95 14.44
			</attr>
		</taxon>


		<taxon id="EPI_ISL_1295638">
			<date value="2021.0712328767124" direction="forwards" units="years"/>
			<attr name="host2">
				Waterfowl
			</attr>
			<attr name="loc">
				60.47 8.47
			</attr>
		</taxon>


		<taxon id="EPI_ISL_2234810">
			<date value="2021.0767123287671" direction="forwards" units="years"/>
			<attr name="host2">
				Seabird
			</attr>
			<attr name="loc">
				41.87 12.57
			</attr>
		</taxon>


		<taxon id="EPI_ISL_1114755">
			<date value="2021.0794520547945" direction="forwards" units="years"/>
			<attr name="host2">
				Dom-gal
			</attr>
			<attr name="loc">
				47.69 41.83
			</attr>
		</taxon>


		<taxon id="EPI_ISL_1114757">
			<date value="2021.0794520547945" direction="forwards" units="years"/>
			<attr name="host2">
				Dom-gal
			</attr>
			<attr name="loc">
				47.69 41.83
			</attr>
		</taxon>


		<taxon id="EPI_ISL_1114758">
			<date value="2021.0794520547945" direction="forwards" units="years"/>
			<attr name="host2">
				Dom-gal
			</attr>
			<attr name="loc">
				47.69 41.83
			</attr>
		</taxon>


		<taxon id="EPI_ISL_1719913">
			<date value="2021.0876712328768" direction="forwards" units="years"/>
			<attr name="host2">
				Dom-gal
			</attr>
			<attr name="loc">
				41.81 25.78
			</attr>
		</taxon>


		<taxon id="EPI_ISL_1665259">
			<date value="2021.0876712328768" direction="forwards" units="years"/>
			<attr name="host2">
				Waterfowl
			</attr>
			<attr name="loc">
				48.21 16.37
			</attr>
		</taxon>


		<taxon id="EPI_ISL_1033028">
			<date value="2021.0904109589042" direction="forwards" units="years"/>
			<attr name="host2">
				Dom-gal
			</attr>
			<attr name="loc">
				49.88 14.94
			</attr>
		</taxon>


		<taxon id="EPI_ISL_1033029">
			<date value="2021.0931506849315" direction="forwards" units="years"/>
			<attr name="host2">
				Dom-gal
			</attr>
			<attr name="loc">
				49.94 16.29
			</attr>
		</taxon>


		<taxon id="EPI_ISL_1057106">
			<date value="2021.0958904109589" direction="forwards" units="years"/>
			<attr name="host2">
				Waterfowl
			</attr>
			<attr name="loc">
				48.95 14.44
			</attr>
		</taxon>


		<taxon id="EPI_ISL_1665257">
			<date value="2021.0958904109589" direction="forwards" units="years"/>
			<attr name="host2">
				Waterfowl
			</attr>
			<attr name="loc">
				48.33 16.06
			</attr>
		</taxon>


		<taxon id="EPI_ISL_1080480">
			<date value="2021.123287671233" direction="forwards" units="years"/>
			<attr name="host2">
				Waterfowl
			</attr>
			<attr name="loc">
				50.66 14.76
			</attr>
		</taxon>


		<taxon id="EPI_ISL_2111625">
			<date value="2021.1260273972603" direction="forwards" units="years"/>
			<attr name="host2">
				Waterfowl
			</attr>
			<attr name="loc">
				54.29 18.15
			</attr>
		</taxon>


		<taxon id="EPI_ISL_1665247">
			<date value="2021.131506849315" direction="forwards" units="years"/>
			<attr name="host2">
				Dom-gal
			</attr>
			<attr name="loc">
				45.96 12.66
			</attr>
		</taxon>


		<taxon id="EPI_ISL_1399231">
			<date value="2021.1342465753426" direction="forwards" units="years"/>
			<attr name="host2">
				Dom-gal
			</attr>
			<attr name="loc">
				49.45 15.64
			</attr>
		</taxon>


		<taxon id="EPI_ISL_1399237">
			<date value="2021.13698630137" direction="forwards" units="years"/>
			<attr name="host2">
				Waterfowl
			</attr>
			<attr name="loc">
				49.88 14.94
			</attr>
		</taxon>


		<taxon id="EPI_ISL_2113167">
			<date value="2021.145205479452" direction="forwards" units="years"/>
			<attr name="host2">
				Waterfowl
			</attr>
			<attr name="loc">
				54.29 18.15
			</attr>
		</taxon>


		<taxon id="EPI_ISL_1399239">
			<date value="2021.1479452054793" direction="forwards" units="years"/>
			<attr name="host2">
				Waterfowl
			</attr>
			<attr name="loc">
				49.66 17.08
			</attr>
		</taxon>


		<taxon id="EPI_ISL_1665248">
			<date value="2021.1479452054793" direction="forwards" units="years"/>
			<attr name="host2">
				Dom-gal
			</attr>
			<attr name="loc">
				45.41 11.88
			</attr>
		</taxon>


		<taxon id="EPI_ISL_1719909">
			<date value="2021.1561643835616" direction="forwards" units="years"/>
			<attr name="host2">
				Waterfowl
			</attr>
			<attr name="loc">
				54.69 25.28
			</attr>
		</taxon>


		<taxon id="EPI_ISL_1719910">
			<date value="2021.1561643835616" direction="forwards" units="years"/>
			<attr name="host2">
				Waterfowl
			</attr>
			<attr name="loc">
				54.69 25.28
			</attr>
		</taxon>


		<taxon id="EPI_ISL_1399233">
			<date value="2021.158904109589" direction="forwards" units="years"/>
			<attr name="host2">
				Dom-gal
			</attr>
			<attr name="loc">
				49.41 13.32
			</attr>
		</taxon>


		<taxon id="EPI_ISL_1279262">
			<date value="2021.164383561644" direction="forwards" units="years"/>
			<attr name="host2">
				Waterfowl
			</attr>
			<attr name="loc">
				45.18 18.81
			</attr>
		</taxon>


		<taxon id="EPI_ISL_2113493">
			<date value="2021.1698630136987" direction="forwards" units="years"/>
			<attr name="host2">
				Waterfowl
			</attr>
			<attr name="loc">
				54.29 18.15
			</attr>
		</taxon>


		<taxon id="EPI_ISL_1399242">
			<date value="2021.172602739726" direction="forwards" units="years"/>
			<attr name="host2">
				Waterfowl
			</attr>
			<attr name="loc">
				49.22 17.77
			</attr>
		</taxon>


		<taxon id="EPI_ISL_1399243">
			<date value="2021.172602739726" direction="forwards" units="years"/>
			<attr name="host2">
				Waterfowl
			</attr>
			<attr name="loc">
				49.66 17.08
			</attr>
		</taxon>


		<taxon id="EPI_ISL_3102060">
			<date value="2021.1753424657534" direction="forwards" units="years"/>
			<attr name="host2">
				Dom-ans
			</attr>
			<attr name="loc">
				52.28 17.35
			</attr>
		</taxon>


		<taxon id="EPI_ISL_2114013">
			<date value="2021.1780821917807" direction="forwards" units="years"/>
			<attr name="host2">
				Waterfowl
			</attr>
			<attr name="loc">
				54.29 18.15
			</attr>
		</taxon>


		<taxon id="EPI_ISL_1399245">
			<date value="2021.1780821917807" direction="forwards" units="years"/>
			<attr name="host2">
				Waterfowl
			</attr>
			<attr name="loc">
				49.73 18.23
			</attr>
		</taxon>


		<taxon id="EPI_ISL_1399241">
			<date value="2021.1780821917807" direction="forwards" units="years"/>
			<attr name="host2">
				Dom-gal
			</attr>
			<attr name="loc">
				49.73 18.23
			</attr>
		</taxon>


		<taxon id="EPI_ISL_1399236">
			<date value="2021.1890410958904" direction="forwards" units="years"/>
			<attr name="host2">
				Dom-gal
			</attr>
			<attr name="loc">
				49.88 14.94
			</attr>
		</taxon>


		<taxon id="EPI_ISL_1697194">
			<date value="2021.194520547945" direction="forwards" units="years"/>
			<attr name="host2">
				Dom-gal
			</attr>
			<attr name="loc">
				49.22 17.77
			</attr>
		</taxon>


		<taxon id="EPI_ISL_1941581">
			<date value="2021.1972602739727" direction="forwards" units="years"/>
			<attr name="host2">
				Waterfowl
			</attr>
			<attr name="loc">
				49.41 13.32
			</attr>
		</taxon>


		<taxon id="EPI_ISL_1719911">
			<date value="2021.213698630137" direction="forwards" units="years"/>
			<attr name="host2">
				Waterfowl
			</attr>
			<attr name="loc">
				54.69 25.28
			</attr>
		</taxon>


		<taxon id="EPI_ISL_1697195">
			<date value="2021.213698630137" direction="forwards" units="years"/>
			<attr name="host2">
				Dom-ans
			</attr>
			<attr name="loc">
				49.94 16.29
			</attr>
		</taxon>


		<taxon id="EPI_ISL_3128523">
			<date value="2021.2219178082191" direction="forwards" units="years"/>
			<attr name="host2">
				Other
			</attr>
			<attr name="loc">
				44.43 5.71
			</attr>
		</taxon>


		<taxon id="EPI_ISL_3102067">
			<date value="2021.2246575342465" direction="forwards" units="years"/>
			<attr name="host2">
				Dom-gal
			</attr>
			<attr name="loc">
				51.89 21.0
			</attr>
		</taxon>


		<taxon id="EPI_ISL_1697192">
			<date value="2021.227397260274" direction="forwards" units="years"/>
			<attr name="host2">
				Dom-ans
			</attr>
			<attr name="loc">
				50.35 15.8
			</attr>
		</taxon>


		<taxon id="EPI_ISL_1697197">
			<date value="2021.2301369863014" direction="forwards" units="years"/>
			<attr name="host2">
				Wild-gal
			</attr>
			<attr name="loc">
				49.41 13.32
			</attr>
		</taxon>


		<taxon id="EPI_ISL_1697182">
			<date value="2021.2301369863014" direction="forwards" units="years"/>
			<attr name="host2">
				Dom-gal
			</attr>
			<attr name="loc">
				50.35 15.8
			</attr>
		</taxon>


		<taxon id="EPI_ISL_1697190">
			<date value="2021.2520547945205" direction="forwards" units="years"/>
			<attr name="host2">
				Dom-gal
			</attr>
			<attr name="loc">
				50.61 13.79
			</attr>
		</taxon>


		<taxon id="EPI_ISL_1941579">
			<date value="2021.2630136986302" direction="forwards" units="years"/>
			<attr name="host2">
				Dom-ans
			</attr>
			<attr name="loc">
				50.35 15.8
			</attr>
		</taxon>


		<taxon id="EPI_ISL_1697183">
			<date value="2021.2630136986302" direction="forwards" units="years"/>
			<attr name="host2">
				Dom-gal
			</attr>
			<attr name="loc">
				50.61 13.79
			</attr>
		</taxon>


		<taxon id="EPI_ISL_1697184">
			<date value="2021.2630136986302" direction="forwards" units="years"/>
			<attr name="host2">
				Dom-gal
			</attr>
			<attr name="loc">
				49.41 13.32
			</attr>
		</taxon>


		<taxon id="EPI_ISL_1697185">
			<date value="2021.2630136986302" direction="forwards" units="years"/>
			<attr name="host2">
				Dom-gal
			</attr>
			<attr name="loc">
				50.35 15.8
			</attr>
		</taxon>


		<taxon id="EPI_ISL_3102077">
			<date value="2021.2657534246575" direction="forwards" units="years"/>
			<attr name="host2">
				Dom-ans
			</attr>
			<attr name="loc">
				54.29 18.15
			</attr>
		</taxon>


		<taxon id="EPI_ISL_1941375">
			<date value="2021.295890410959" direction="forwards" units="years"/>
			<attr name="host2">
				Dom-gal
			</attr>
			<attr name="loc">
				50.35 15.8
			</attr>
		</taxon>


		<taxon id="EPI_ISL_3102066">
			<date value="2021.3013698630136" direction="forwards" units="years"/>
			<attr name="host2">
				Dom-gal
			</attr>
			<attr name="loc">
				52.28 17.35
			</attr>
		</taxon>


		<taxon id="EPI_ISL_3102078">
			<date value="2021.3068493150686" direction="forwards" units="years"/>
			<attr name="host2">
				Waterfowl
			</attr>
			<attr name="loc">
				53.47 15.18
			</attr>
		</taxon>


		<taxon id="EPI_ISL_3102056">
			<date value="2021.309589041096" direction="forwards" units="years"/>
			<attr name="host2">
				Dom-gal
			</attr>
			<attr name="loc">
				41.93 25.56
			</attr>
		</taxon>


		<taxon id="EPI_ISL_3102080">
			<date value="2021.3205479452056" direction="forwards" units="years"/>
			<attr name="host2">
				Dom-gal
			</attr>
			<attr name="loc">
				48.46 14.22
			</attr>
		</taxon>


		<taxon id="EPI_ISL_3102065">
			<date value="2021.33698630137" direction="forwards" units="years"/>
			<attr name="host2">
				Waterfowl
			</attr>
			<attr name="loc">
				52.28 17.35
			</attr>
		</taxon>


		<taxon id="EPI_ISL_3102058">
			<date value="2021.3424657534247" direction="forwards" units="years"/>
			<attr name="host2">
				Dom-gal
			</attr>
			<attr name="loc">
				42.2 24.87
			</attr>
		</taxon>


		<taxon id="EPI_ISL_2681044">
			<date value="2021.3424657534247" direction="forwards" units="years"/>
			<attr name="host2">
				Dom-gal
			</attr>
			<attr name="loc">
				46.48 24.46
			</attr>
		</taxon>


		<taxon id="EPI_ISL_3102072">
			<date value="2021.3479452054794" direction="forwards" units="years"/>
			<attr name="host2">
				Dom-gal
			</attr>
			<attr name="loc">
				51.89 21.0
			</attr>
		</taxon>


		<taxon id="EPI_ISL_3102074">
			<date value="2021.3643835616438" direction="forwards" units="years"/>
			<attr name="host2">
				Dom-gal
			</attr>
			<attr name="loc">
				53.87 20.7
			</attr>
		</taxon>


		<taxon id="EPI_ISL_3102069">
			<date value="2021.3643835616438" direction="forwards" units="years"/>
			<attr name="host2">
				Dom-gal
			</attr>
			<attr name="loc">
				51.89 21.0
			</attr>
		</taxon>


		<taxon id="EPI_ISL_3128529">
			<date value="2021.3808219178081" direction="forwards" units="years"/>
			<attr name="host2">
				Dom-gal
			</attr>
			<attr name="loc">
				42.89 20.87
			</attr>
		</taxon>


		<taxon id="EPI_ISL_3128527">
			<date value="2021.4191780821918" direction="forwards" units="years"/>
			<attr name="host2">
				Dom-ans
			</attr>
			<attr name="loc">
				42.23 21.26
			</attr>
		</taxon>


		<taxon id="EPI_ISL_3128534">
			<date value="2021.4246575342465" direction="forwards" units="years"/>
			<attr name="host2">
				Dom-gal
			</attr>
			<attr name="loc">
				41.15 20.17
			</attr>
		</taxon>


		<taxon id="EPI_ISL_237553">
			<date value="2016.7972602739726" direction="forwards" units="years"/>
			<attr name="host2">
				Waterfowl
			</attr>
			<attr name="loc">
				28.7 77.1
			</attr>
		</taxon>


		<taxon id="EPI_ISL_412984">
			<date value="2016.8739726027397" direction="forwards" units="years"/>
			<attr name="host2">
				Dom-gal
			</attr>
			<attr name="loc">
				32.43 53.69
			</attr>
		</taxon>


		<taxon id="EPI_ISL_378634">
			<date value="2016.8986301369864" direction="forwards" units="years"/>
			<attr name="host2">
				Waterfowl
			</attr>
			<attr name="loc">
				35.86 104.2
			</attr>
		</taxon>


		<taxon id="EPI_ISL_412990">
			<date value="2016.9260273972602" direction="forwards" units="years"/>
			<attr name="host2">
				Dom-gal
			</attr>
			<attr name="loc">
				32.43 53.69
			</attr>
		</taxon>


		<taxon id="EPI_ISL_707663">
			<date value="2016.9671232876713" direction="forwards" units="years"/>
			<attr name="host2">
				Waterfowl
			</attr>
			<attr name="loc">
				42.52 87.54
			</attr>
		</taxon>


		<taxon id="EPI_ISL_707666">
			<date value="2016.9671232876713" direction="forwards" units="years"/>
			<attr name="host2">
				Waterfowl
			</attr>
			<attr name="loc">
				42.52 87.54
			</attr>
		</taxon>


		<taxon id="EPI_ISL_707581">
			<date value="2016.9671232876713" direction="forwards" units="years"/>
			<attr name="host2">
				Dom-ans
			</attr>
			<attr name="loc">
				42.52 87.54
			</attr>
		</taxon>


		<taxon id="EPI_ISL_412987">
			<date value="2016.9698630136986" direction="forwards" units="years"/>
			<attr name="host2">
				Dom-gal
			</attr>
			<attr name="loc">
				32.43 53.69
			</attr>
		</taxon>


		<taxon id="EPI_ISL_295494">
			<date value="2016.972602739726" direction="forwards" units="years"/>
			<attr name="host2">
				Waterfowl
			</attr>
			<attr name="loc">
				35.86 104.2
			</attr>
		</taxon>


		<taxon id="EPI_ISL_400490">
			<date value="2016.9835616438356" direction="forwards" units="years"/>
			<attr name="host2">
				Waterfowl
			</attr>
			<attr name="loc">
				37.24 111.86
			</attr>
		</taxon>


		<taxon id="EPI_ISL_400491">
			<date value="2016.9835616438356" direction="forwards" units="years"/>
			<attr name="host2">
				Waterfowl
			</attr>
			<attr name="loc">
				37.24 111.86
			</attr>
		</taxon>


		<taxon id="EPI_ISL_295493">
			<date value="2016.9945205479453" direction="forwards" units="years"/>
			<attr name="host2">
				Waterfowl
			</attr>
			<attr name="loc">
				35.86 104.2
			</attr>
		</taxon>


		<taxon id="EPI_ISL_885149">
			<date value="2017" direction="forwards" units="years" uncertainty="1.0"/>
			<attr name="host2">
				Seabird
			</attr>
			<attr name="loc">
				1.37 23.29
			</attr>
		</taxon>


		<taxon id="EPI_ISL_285620">
			<date value="2017" direction="forwards" units="years" uncertainty="1.0"/>
			<attr name="host2">
				Dom-gal
			</attr>
			<attr name="loc">
				30.85 30.34
			</attr>
		</taxon>


		<taxon id="EPI_ISL_285622">
			<date value="2017" direction="forwards" units="years" uncertainty="1.0"/>
			<attr name="host2">
				Dom-ans
			</attr>
			<attr name="loc">
				30.85 30.34
			</attr>
		</taxon>


		<taxon id="EPI_ISL_308807">
			<date value="2017.041095890411" direction="forwards" units="years"/>
			<attr name="host2">
				Dom-ans
			</attr>
			<attr name="loc">
				7.37 12.35
			</attr>
		</taxon>


		<taxon id="EPI_ISL_379227">
			<date value="2017.041095890411" direction="forwards" units="years"/>
			<attr name="host2">
				Dom-gal
			</attr>
			<attr name="loc">
				1.37 23.29
			</attr>
		</taxon>


		<taxon id="EPI_ISL_379228">
			<date value="2017.041095890411" direction="forwards" units="years"/>
			<attr name="host2">
				Dom-ans
			</attr>
			<attr name="loc">
				1.37 23.29
			</attr>
		</taxon>


		<taxon id="EPI_ISL_387137">
			<date value="2017.0082191780823" direction="forwards" units="years"/>
			<attr name="host2">
				Dom-gal
			</attr>
			<attr name="loc">
				26.82 30.8
			</attr>
		</taxon>


		<taxon id="EPI_ISL_400493">
			<date value="2017.0328767123287" direction="forwards" units="years"/>
			<attr name="host2">
				Waterfowl
			</attr>
			<attr name="loc">
				30.74 112.24
			</attr>
		</taxon>


		<taxon id="EPI_ISL_400494">
			<date value="2017.0328767123287" direction="forwards" units="years"/>
			<attr name="host2">
				Waterfowl
			</attr>
			<attr name="loc">
				30.74 112.24
			</attr>
		</taxon>


		<taxon id="EPI_ISL_268021">
			<date value="2017.0328767123287" direction="forwards" units="years"/>
			<attr name="host2">
				Dom-ans
			</attr>
			<attr name="loc">
				30.73 31.72
			</attr>
		</taxon>


		<taxon id="EPI_ISL_387139">
			<date value="2017.0712328767124" direction="forwards" units="years"/>
			<attr name="host2">
				Waterfowl
			</attr>
			<attr name="loc">
				26.82 30.8
			</attr>
		</taxon>


		<taxon id="EPI_ISL_387135">
			<date value="2017.1260273972603" direction="forwards" units="years"/>
			<attr name="host2">
				Waterfowl
			</attr>
			<attr name="loc">
				26.82 30.8
			</attr>
		</taxon>


		<taxon id="EPI_ISL_387136">
			<date value="2017.1534246575343" direction="forwards" units="years"/>
			<attr name="host2">
				Waterfowl
			</attr>
			<attr name="loc">
				26.82 30.8
			</attr>
		</taxon>


		<taxon id="EPI_ISL_696912">
			<date value="2017.2109589041097" direction="forwards" units="years"/>
			<attr name="host2">
				Waterfowl
			</attr>
			<attr name="loc">
				42.52 87.54
			</attr>
		</taxon>


		<taxon id="EPI_ISL_707583">
			<date value="2017.304109589041" direction="forwards" units="years"/>
			<attr name="host2">
				Dom-ans
			</attr>
			<attr name="loc">
				42.52 87.54
			</attr>
		</taxon>


		<taxon id="EPI_ISL_308804">
			<date value="2017.3643835616438" direction="forwards" units="years"/>
			<attr name="host2">
				Dom-ans
			</attr>
			<attr name="loc">
				-4.04 21.76
			</attr>
		</taxon>


		<taxon id="EPI_ISL_308803">
			<date value="2017.3671232876711" direction="forwards" units="years"/>
			<attr name="host2">
				Dom-ans
			</attr>
			<attr name="loc">
				-4.04 21.76
			</attr>
		</taxon>


		<taxon id="EPI_ISL_308802">
			<date value="2017.3698630136987" direction="forwards" units="years"/>
			<attr name="host2">
				Dom-ans
			</attr>
			<attr name="loc">
				-4.04 21.76
			</attr>
		</taxon>


		<taxon id="EPI_ISL_707670">
			<date value="2017.6438356164383" direction="forwards" units="years"/>
			<attr name="host2">
				Waterfowl
			</attr>
			<attr name="loc">
				42.52 87.54
			</attr>
		</taxon>


		<taxon id="EPI_ISL_707671">
			<date value="2017.6438356164383" direction="forwards" units="years"/>
			<attr name="host2">
				Waterfowl
			</attr>
			<attr name="loc">
				42.52 87.54
			</attr>
		</taxon>


		<taxon id="EPI_ISL_707674">
			<date value="2017.6438356164383" direction="forwards" units="years"/>
			<attr name="host2">
				Waterfowl
			</attr>
			<attr name="loc">
				42.52 87.54
			</attr>
		</taxon>


		<taxon id="EPI_ISL_413004">
			<date value="2017.717808219178" direction="forwards" units="years"/>
			<attr name="host2">
				Dom-gal
			</attr>
			<attr name="loc">
				32.43 53.69
			</attr>
		</taxon>


		<taxon id="EPI_ISL_696740">
			<date value="2017.841095890411" direction="forwards" units="years"/>
			<attr name="host2">
				Dom-ans
			</attr>
			<attr name="loc">
				27.63 111.86
			</attr>
		</taxon>


		<taxon id="EPI_ISL_344546">
			<date value="2018.3972602739725" direction="forwards" units="years"/>
			<attr name="host2">
				Dom-ans
			</attr>
			<attr name="loc">
				30.01 31.21
			</attr>
		</taxon>


		<taxon id="EPI_ISL_697979">
			<date value="2018.717808219178" direction="forwards" units="years"/>
			<attr name="host2">
				Dom-ans
			</attr>
			<attr name="loc">
				42.52 87.54
			</attr>
		</taxon>


		<taxon id="EPI_ISL_626648">
			<date value="2020.7561643835616" direction="forwards" units="years"/>
			<attr name="host2">
				Waterfowl
			</attr>
			<attr name="loc">
				55.06 73.72
			</attr>
		</taxon>


		<taxon id="EPI_ISL_603133">
			<date value="2020.7945205479452" direction="forwards" units="years"/>
			<attr name="host2">
				Waterfowl
			</attr>
			<attr name="loc">
				52.13 5.29
			</attr>
		</taxon>


		<taxon id="EPI_ISL_644737">
			<date value="2020.8328767123287" direction="forwards" units="years"/>
			<attr name="host2">
				Other
			</attr>
			<attr name="loc">
				55.46 11.72
			</attr>
		</taxon>


		<taxon id="EPI_ISL_660264">
			<date value="2020.8849315068494" direction="forwards" units="years"/>
			<attr name="host2">
				Dom-gal
			</attr>
			<attr name="loc">
				51.01 3.73
			</attr>
		</taxon>


		<taxon id="EPI_ISL_683752">
			<date value="2020.8931506849315" direction="forwards" units="years"/>
			<attr name="host2">
				Waterfowl
			</attr>
			<attr name="loc">
				45.44 12.32
			</attr>
		</taxon>


		<taxon id="EPI_ISL_956412">
			<date value="2020.8986301369864" direction="forwards" units="years"/>
			<attr name="host2">
				Waterfowl
			</attr>
			<attr name="loc">
				45.94 13.62
			</attr>
		</taxon>


		<taxon id="EPI_ISL_683999">
			<date value="2020.9013698630138" direction="forwards" units="years"/>
			<attr name="host2">
				Waterfowl
			</attr>
			<attr name="loc">
				55.38 -3.44
			</attr>
		</taxon>


		<taxon id="EPI_ISL_683997">
			<date value="2020.9013698630138" direction="forwards" units="years"/>
			<attr name="host2">
				Waterfowl
			</attr>
			<attr name="loc">
				55.38 -3.44
			</attr>
		</taxon>


		<taxon id="EPI_ISL_1205489">
			<date value="2020.9616438356165" direction="forwards" units="years"/>
			<attr name="host2">
				Waterfowl
			</attr>
			<attr name="loc">
				54.22 9.7
			</attr>
		</taxon>


		<taxon id="EPI_ISL_1665267">
			<date value="2020.9835616438356" direction="forwards" units="years"/>
			<attr name="host2">
				Waterfowl
			</attr>
			<attr name="loc">
				46.15 15.0
			</attr>
		</taxon>


		<taxon id="EPI_ISL_2234808">
			<date value="2021.0027397260274" direction="forwards" units="years"/>
			<attr name="host2">
				Waterfowl
			</attr>
			<attr name="loc">
				53.41 8.24
			</attr>
		</taxon>


		<taxon id="EPI_ISL_2234821">
			<date value="2021.021917808219" direction="forwards" units="years"/>
			<attr name="host2">
				Waterfowl
			</attr>
			<attr name="loc">
				45.94 24.97
			</attr>
		</taxon>


		<taxon id="EPI_ISL_2234822">
			<date value="2021.0328767123287" direction="forwards" units="years"/>
			<attr name="host2">
				Waterfowl
			</attr>
			<attr name="loc">
				45.94 24.97
			</attr>
		</taxon>


		<taxon id="EPI_ISL_2234823">
			<date value="2021.0383561643835" direction="forwards" units="years"/>
			<attr name="host2">
				Waterfowl
			</attr>
			<attr name="loc">
				45.94 24.97
			</attr>
		</taxon>


		<taxon id="EPI_ISL_1665262">
			<date value="2021.041095890411" direction="forwards" units="years"/>
			<attr name="host2">
				Waterfowl
			</attr>
			<attr name="loc">
				48.11 17.11
			</attr>
		</taxon>


		<taxon id="EPI_ISL_1259399">
			<date value="2021.0493150684931" direction="forwards" units="years"/>
			<attr name="host2">
				Waterfowl
			</attr>
			<attr name="loc">
				48.88 -0.52
			</attr>
		</taxon>


		<taxon id="EPI_ISL_2234824">
			<date value="2021.0602739726028" direction="forwards" units="years"/>
			<attr name="host2">
				Waterfowl
			</attr>
			<attr name="loc">
				45.94 24.97
			</attr>
		</taxon>


		<taxon id="EPI_ISL_1259397">
			<date value="2021.0602739726028" direction="forwards" units="years"/>
			<attr name="host2">
				Other
			</attr>
			<attr name="loc">
				48.88 -0.52
			</attr>
		</taxon>


		<taxon id="EPI_ISL_2234809">
			<date value="2021.0876712328768" direction="forwards" units="years"/>
			<attr name="host2">
				Seabird
			</attr>
			<attr name="loc">
				46.82 8.23
			</attr>
		</taxon>


		<taxon id="EPI_ISL_1123361">
			<date value="2021.1123287671232" direction="forwards" units="years"/>
			<attr name="host2">
				Dom-gal
			</attr>
			<attr name="loc">
				56.21 -3.15
			</attr>
		</taxon>


		<taxon id="EPI_ISL_1665249">
			<date value="2021.1479452054793" direction="forwards" units="years"/>
			<attr name="host2">
				Dom-gal
			</attr>
			<attr name="loc">
				45.81 21.33
			</attr>
		</taxon>


		<taxon id="EPI_ISL_3102054">
			<date value="2021.2438356164384" direction="forwards" units="years"/>
			<attr name="host2">
				Seabird
			</attr>
			<attr name="loc">
				42.23 27.77
			</attr>
		</taxon>


		<taxon id="EPI_ISL_3102081">
			<date value="2021.268493150685" direction="forwards" units="years"/>
			<attr name="host2">
				Waterfowl
			</attr>
			<attr name="loc">
				45.42 29.29
			</attr>
		</taxon>


		<taxon id="EPI_ISL_3135897">
			<date value="2021.282191780822" direction="forwards" units="years"/>
			<attr name="host2">
				Dom-gal
			</attr>
			<attr name="loc">
				47.47 21.55
			</attr>
		</taxon>

	</taxa>


	<!-- paste your sequences here -->



	<patterns id="patterns" from="1" strip="false">
		<alignment idref="alignment"/>
	</patterns>



	<generalDataType id="host2.dataType">
		<state code="Waterfowl"/>
		<state code="Wild-gal"/>
		<state code="Dom-ans"/>
		<state code="Dom-gal"/>
		<state code="Seabird"/>
		<state code="Other"/>
	</generalDataType>



	<attributePatterns id="host2.pattern" attribute="host2">
		<taxa idref="taxa"/>
		<generalDataType idref="host2.dataType"/>
	</attributePatterns>



	<constantSize id="constant" units="years">
		<populationSize>
			<parameter id="constant.popSize" value="1.0" lower="0.0"/>
		</populationSize>
	</constantSize>



	<empiricalTreeDistributionModel id="treeModel" fileName="./ext_0_0_0_0_0_0_0_0_MP.combined.trees">
		<taxa idref="taxa"/>
		<nodeTraits rootNode="false" internalNodes="false" leafNodes="true" traitDimension="2" name="loc">
			<parameter id="leafTraits"/>
		</nodeTraits>
	</empiricalTreeDistributionModel>
	<statistic id="treeModel.currentTree" name="Current Tree">
		<empiricalTreeDistributionModel idref="treeModel"/>
	</statistic>



	<coalescentLikelihood id="coalescent">
		<model>
			<constantSize idref="constant"/>
		</model>
		<populationTree>
			<treeModel idref="treeModel"/>
		</populationTree>
	</coalescentLikelihood>



	<strictClockBranchRates id="host2.branchRates">
		<rate>
			<parameter id="host2.clock.rate" value="1.0" lower="0.0"/>
		</rate>
	</strictClockBranchRates>
	<rateStatistic id="host2.meanRate" name="host2.meanRate" mode="mean" internal="true" external="true">
		<treeModel idref="treeModel"/>
		<strictClockBranchRates idref="host2.branchRates"/>
	</rateStatistic>

	<generalSubstitutionModel id="host2.model" randomizeIndicator="false">
		<generalDataType idref="host2.dataType"/>
		<frequencies>
			<frequencyModel id="host2.frequencyModel" normalize="true">
				<generalDataType idref="host2.dataType"/>
				<frequencies>
					<parameter id="host2.frequencies" dimension="6"/>
				</frequencies>
			</frequencyModel>
		</frequencies>

		<rates>
			<parameter id="host2.rates" dimension="30" value="1.0" lower="0.0"/>
		</rates>
		<rateIndicator>
			<parameter id="host2.indicators" dimension="30" value="1.0"/>
		</rateIndicator>
	</generalSubstitutionModel>
	<sumStatistic id="host2.nonZeroRates" elementwise="true">
		<parameter idref="host2.indicators"/>
	</sumStatistic>
	<productStatistic id="host2.actualRates" elementwise="false">
		<parameter idref="host2.indicators"/>
		<parameter idref="host2.rates"/>
	</productStatistic>
	<siteModel id="host2.siteModel">
		<substitutionModel>
			<generalSubstitutionModel idref="host2.model"/>
		</substitutionModel>
	</siteModel>

	<!-- Likelihood for tree given discrete trait data                           -->
	<ancestralTreeLikelihood id="host2.treeLikelihood" stateTagName="host2.states" useUniformization="true" saveCompleteHistory="false" logCompleteHistory="false">
		<attributePatterns idref="host2.pattern"/>
		<treeModel idref="treeModel"/>
		<siteModel idref="host2.siteModel"/>
		<generalSubstitutionModel idref="host2.model"/>
		<generalSubstitutionModel idref="host2.model"/>
		<strictClockBranchRates idref="host2.branchRates"/>

		<!-- The root state frequencies                                              -->
		<frequencyModel id="host2.root.frequencyModel" normalize="true">
			<generalDataType idref="host2.dataType"/>
			<frequencies>
				<parameter id="host2.root.frequencies" dimension="6"/>
			</frequencies>
		</frequencyModel>
	</ancestralTreeLikelihood>



	<multivariateDiffusionModel id="loc.diffusionModel">
		<precisionMatrix>
			<matrixParameter id="loc.precision">
				<parameter id="loc.precision.col1" value="0.05 0.002"/>
				<parameter id="loc.precision.col2" value="0.002 0.05"/>
			</matrixParameter>
		</precisionMatrix>
	</multivariateDiffusionModel>

	<multivariateWishartPrior id="loc.precisionPrior" df="2">
		<scaleMatrix>
			<matrixParameter>
				<parameter value="1.0 0.0"/>
				<parameter value="0.0 1.0"/>
			</matrixParameter>
		</scaleMatrix>
		<data>
			<parameter idref="loc.precision"/>
		</data>
	</multivariateWishartPrior>

	<arbitraryBranchRates id="loc.diffusion.branchRates">
		<treeModel idref="treeModel"/>
		<rates>
			<parameter id="loc.diffusion.rates" lower="0.0"/>
		</rates>
	</arbitraryBranchRates>
	<distributionLikelihood id="loc.diffusion.prior">
		<data>
			<parameter idref="loc.diffusion.rates"/>
		</data>
		<distribution>
			<onePGammaDistributionModel>
				<shape>
					<!-- half DF (i.e., df = 1)                                                  -->
					<parameter value="0.5"/>
				</shape>
			</onePGammaDistributionModel>
		</distribution>
	</distributionLikelihood>

	<multivariateTraitLikelihood id="loc.traitLikelihood" traitName="loc" useTreeLength="true" scaleByTime="true" reportAsMultivariate="true" reciprocalRates="true" integrateInternalTraits="true">
		<multivariateDiffusionModel idref="loc.diffusionModel"/>
		<treeModel idref="treeModel"/>
		<traitParameter>
			<parameter id="leaf.loc"/>
		</traitParameter>
		<jitter window="0.001 0.001" duplicatesOnly="true">
			<parameter idref="leaf.loc"/>
		</jitter>
		<conjugateRootPrior>
			<meanParameter>
				<parameter value="0.0 0.0"/>
			</meanParameter>
			<priorSampleSize>
				<parameter value="0.000001"/>
			</priorSampleSize>
		</conjugateRootPrior>
		<arbitraryBranchRates idref="loc.diffusion.branchRates"/>
	</multivariateTraitLikelihood>
	<correlation id="loc.correlation" dimension1="1" dimension2="2">
		<matrixParameter idref="loc.precision"/>
	</correlation>
	<matrixInverse id="loc.varCovar">
		<matrixParameter idref="loc.precision"/>
	</matrixInverse>
	<continuousDiffusionStatistic id="loc.diffusionRate" greatCircleDistance="true">
		<multivariateTraitLikelihood idref="loc.traitLikelihood"/>
	</continuousDiffusionStatistic>



	<treeLengthStatistic id="treeLength">
		<treeModel idref="treeModel"/>
	</treeLengthStatistic>



	<operators id="operators" optimizationSchedule="log">
		<scaleOperator scaleFactor="0.75" weight="3">
			<parameter idref="host2.clock.rate"/>
		</scaleOperator>

		<scaleOperator scaleFactor="0.75" weight="30">
			<parameter idref="loc.diffusion.rates"/>
		</scaleOperator>
		<scaleOperator scaleFactor="0.75" weight="15" scaleAllIndependently="true">
			<parameter idref="host2.rates"/>
		</scaleOperator>
		<bitFlipOperator weight="7">
			<parameter idref="host2.indicators"/>
		</bitFlipOperator>
		<deltaExchange delta="0.75" weight="1">
			<parameter idref="host2.root.frequencies"/>
		</deltaExchange>

		<empiricalTreeDistributionOperator weight="0.2">
			<empiricalTreeDistributionModel idref="treeModel"/>
		</empiricalTreeDistributionOperator>

		<precisionGibbsOperator weight="2">
			<multivariateTraitLikelihood idref="loc.traitLikelihood"/>
			<multivariateWishartPrior idref="loc.precisionPrior"/>
		</precisionGibbsOperator>
	</operators>



	<mcmc id="mcmc" chainLength="50000000" autoOptimize="true">
		<joint id="joint">
			<prior id="prior">
				<ctmcScalePrior>
					<ctmcScale>
						<parameter idref="host2.clock.rate"/>
					</ctmcScale>
					<treeModel idref="treeModel"/>
				</ctmcScalePrior>

				<poissonPrior mean="5.0" offset="0.0">
					<statistic idref="host2.nonZeroRates"/>
				</poissonPrior>
				<uniformPrior lower="0.0" upper="1.0">
					<parameter idref="host2.frequencies"/>
				</uniformPrior>
				<cachedPrior>
					<gammaPrior shape="1.0" scale="1.0" offset="0.0">
						<parameter idref="host2.rates"/>
					</gammaPrior>
					<parameter idref="host2.rates"/>
				</cachedPrior>
				<uniformPrior lower="0.0" upper="1.0">
					<parameter idref="host2.root.frequencies"/>
				</uniformPrior>

				<coalescentLikelihood idref="coalescent"/>
				<strictClockBranchRates idref="host2.branchRates"/>
				<distributionLikelihood idref="loc.diffusion.prior"/>
				<multivariateWishartPrior idref="loc.precisionPrior"/>
				<generalSubstitutionModel idref="host2.model"/>
			</prior>

			<likelihood id="likelihood">
				<multivariateTraitLikelihood idref="loc.traitLikelihood"/>
				<ancestralTreeLikelihood idref="host2.treeLikelihood"/>
			</likelihood>
		</joint>
		<operators idref="operators"/>


		<!-- write log to screen                                                     -->
		<log id="screenLog" logEvery="5000">
			<column label="Joint" dp="4" width="12">
				<joint idref="joint"/>
			</column>
			<column label="Prior" dp="4" width="12">
				<prior idref="prior"/>
			</column>
			<column label="Likelihood" dp="4" width="12">
				<likelihood idref="likelihood"/>
			</column>

			<column label="host2.clock.rate" sf="6" width="12">
				<parameter idref="host2.clock.rate"/>
			</column>

			<column label="host2.nonZeroRates" dp="0" width="6">
				<sumStatistic idref="host2.nonZeroRates"/>
			</column>
		</log>

		<!-- write log to file                                                       -->
		<log id="fileLog" logEvery="5000" fileName="ext_0_0_0_0_0_0_0_0_MP.emp.log" overwrite="false">
			<joint idref="joint"/>
			<prior idref="prior"/>
			<likelihood idref="likelihood"/>

			<treeLengthStatistic idref="treeLength"/>
			<parameter idref="host2.clock.rate"/>
			<rateStatistic idref="host2.meanRate"/>

			<matrixParameter idref="loc.precision"/>
			<correlation idref="loc.correlation"/>
			<matrixInverse idref="loc.varCovar"/>
			<continuousDiffusionStatistic idref="loc.diffusionRate"/>

			<parameter idref="host2.rates"/>
			<parameter idref="host2.indicators"/>

			<sumStatistic idref="host2.nonZeroRates"/>

			<strictClockBranchRates idref="host2.branchRates"/>

			<multivariateTraitLikelihood idref="loc.traitLikelihood"/>
			<ancestralTreeLikelihood idref="host2.treeLikelihood"/>
			<!-- <coalescentLikelihood idref="coalescent"/> -->
		</log>

		<log id="ext_0_0_0_0_0_0_0_0_MP.emp.host2rateMatrixLog" logEvery="5000" fileName="ext_0_0_0_0_0_0_0_0_MP.emp.host2.rates.log">
			<parameter idref="host2.rates"/>
			<parameter idref="host2.indicators"/>
			<sumStatistic idref="host2.nonZeroRates"/>
		</log>

		<!-- write tree log to file                                                  -->
		<logTree id="treeFileLog" logEvery="5000" nexusFormat="true" fileName="ext_0_0_0_0_0_0_0_0_MP.emp.trees" sortTranslationTable="true">
			<treeModel idref="treeModel"/>
			<trait name="rate" tag="host2.rate">
				<strictClockBranchRates idref="host2.branchRates"/>
			</trait>
			<joint idref="joint"/>

			<trait name="loc" tag="loc">
				<multivariateTraitLikelihood idref="loc.traitLikelihood"/>
			</trait>
			<trait name="host2.states" tag="host2">
				<ancestralTreeLikelihood idref="host2.treeLikelihood"/>
			</trait>

			<multivariateDiffusionModel idref="loc.diffusionModel"/>
			<multivariateTraitLikelihood idref="loc.traitLikelihood"/>
			<trait name="rate" tag="loc.rate">
				<arbitraryBranchRates idref="loc.diffusion.branchRates"/>
			</trait>
		</logTree>
	</mcmc>



	<report>
		<property name="timer">
			<mcmc idref="mcmc"/>
		</property>
	</report>

</beast>
